{
  "classname": null,
  "name": null,
  "animation": {
    "classname": null,
    "name": "AnimationManager",
    "actionlist": []
  },
  "dataScale": 1,
  "designHeight": 640,
  "designWidth": 960,
  "textures": [
    "ui1.plist"
  ],
  "texturesPng": [
    "ui1.plist"
  ],
  "version": "1.5.0.1",
  "widgetTree": {
    "classname": "Panel",
    "name": null,
    "children": [
      {
        "classname": "Panel",
        "name": null,
        "children": [
          {
            "classname": "ImageView",
            "name": null,
            "children": [
              {
                "classname": "ImageView",
                "name": null,
                "children": [],
                "options": {
                  "__type": "ImageViewSurrogate:#EditorCommon.JsonModel.Component.GUI",
                  "classname": "ImageView",
                  "name": "Image_34",
                  "ZOrder": 0,
                  "actiontag": 45670269,
                  "anchorPointX": 0.5,
                  "anchorPointY": 0.5,
                  "classType": "CocoStudio.EngineAdapterWrap.CSImageView",
                  "colorB": 255,
                  "colorG": 255,
                  "colorR": 255,
                  "customProperty": "",
                  "flipX": false,
                  "flipY": false,
                  "height": 60,
                  "ignoreSize": false,
                  "layoutParameter": null,
                  "opacity": 255,
                  "positionPercentX": -0.4,
                  "positionPercentY": 0.365,
                  "positionType": 0,
                  "rotation": 0,
                  "scaleX": 1,
                  "scaleY": 1,
                  "sizePercentX": 0.115384616,
                  "sizePercentY": 0.15,
                  "sizeType": 0,
                  "tag": 62,
                  "touchAble": false,
                  "useMergedTexture": false,
                  "visible": true,
                  "width": 60,
                  "x": -208,
                  "y": 146,
                  "capInsetsHeight": 1,
                  "capInsetsWidth": 1,
                  "capInsetsX": 0,
                  "capInsetsY": 0,
                  "fileName": null,
                  "fileNameData": {
                    "path": "ui24.png",
                    "plistFile": "ui1.plist",
                    "resourceType": 1
                  },
                  "scale9Enable": false,
                  "scale9Height": 60,
                  "scale9Width": 60
                }
              },
              {
                "classname": "ImageView",
                "name": null,
                "children": [
                  {
                    "classname": "Label",
                    "name": null,
                    "children": [],
                    "options": {
                      "__type": "LabelSurrogate:#EditorCommon.JsonModel.Component.GUI",
                      "classname": "Label",
                      "name": "Label_25",
                      "ZOrder": 0,
                      "actiontag": 8091824,
                      "anchorPointX": 0.5,
                      "anchorPointY": 0.5,
                      "classType": "CocoStudio.EngineAdapterWrap.CSLabel",
                      "colorB": 0,
                      "colorG": 215,
                      "colorR": 255,
                      "customProperty": "",
                      "flipX": false,
                      "flipY": false,
                      "height": 39,
                      "ignoreSize": true,
                      "layoutParameter": null,
                      "opacity": 255,
                      "positionPercentX": 0,
                      "positionPercentY": 0,
                      "positionType": 0,
                      "rotation": 0,
                      "scaleX": 1,
                      "scaleY": 1,
                      "sizePercentX": 0.25,
                      "sizePercentY": 0.45,
                      "sizeType": 0,
                      "tag": 248,
                      "touchAble": false,
                      "useMergedTexture": false,
                      "visible": true,
                      "width": 120,
                      "x": 0,
                      "y": 0,
                      "areaHeight": 0,
                      "areaWidth": 0,
                      "fontFile": null,
                      "fontName": "微软雅黑",
                      "fontSize": 30,
                      "hAlignment": 0,
                      "text": "出售道具",
                      "touchScaleEnable": false,
                      "vAlignment": 0
                    }
                  }
                ],
                "options": {
                  "__type": "ImageViewSurrogate:#EditorCommon.JsonModel.Component.GUI",
                  "classname": "ImageView",
                  "name": "Image_39",
                  "ZOrder": 0,
                  "actiontag": 64457076,
                  "anchorPointX": 0.5,
                  "anchorPointY": 0.5,
                  "classType": "CocoStudio.EngineAdapterWrap.CSImageView",
                  "colorB": 255,
                  "colorG": 255,
                  "colorR": 255,
                  "customProperty": "",
                  "flipX": false,
                  "flipY": false,
                  "height": 60,
                  "ignoreSize": false,
                  "layoutParameter": null,
                  "opacity": 255,
                  "positionPercentX": -0.005769231,
                  "positionPercentY": 0.365,
                  "positionType": 0,
                  "rotation": 0,
                  "scaleX": 1,
                  "scaleY": 1,
                  "sizePercentX": 0.7307692,
                  "sizePercentY": 0.15,
                  "sizeType": 0,
                  "tag": 67,
                  "touchAble": false,
                  "useMergedTexture": false,
                  "visible": true,
                  "width": 380,
                  "x": -3,
                  "y": 146,
                  "capInsetsHeight": 1,
                  "capInsetsWidth": 1,
                  "capInsetsX": 0,
                  "capInsetsY": 0,
                  "fileName": null,
                  "fileNameData": {
                    "path": "ui25.png",
                    "plistFile": "ui1.plist",
                    "resourceType": 1
                  },
                  "scale9Enable": false,
                  "scale9Height": 60,
                  "scale9Width": 380
                }
              },
              {
                "classname": "ImageView",
                "name": null,
                "children": [],
                "options": {
                  "__type": "ImageViewSurrogate:#EditorCommon.JsonModel.Component.GUI",
                  "classname": "ImageView",
                  "name": "Image_34_0",
                  "ZOrder": 0,
                  "actiontag": 32459037,
                  "anchorPointX": 0.5,
                  "anchorPointY": 0.5,
                  "classType": "CocoStudio.EngineAdapterWrap.CSImageView",
                  "colorB": 255,
                  "colorG": 255,
                  "colorR": 255,
                  "customProperty": "",
                  "flipX": true,
                  "flipY": false,
                  "height": 60,
                  "ignoreSize": false,
                  "layoutParameter": null,
                  "opacity": 255,
                  "positionPercentX": 0.403846145,
                  "positionPercentY": 0.365,
                  "positionType": 0,
                  "rotation": 0,
                  "scaleX": 1,
                  "scaleY": 1,
                  "sizePercentX": 0.115384616,
                  "sizePercentY": 0.15,
                  "sizeType": 0,
                  "tag": 80,
                  "touchAble": false,
                  "useMergedTexture": false,
                  "visible": true,
                  "width": 60,
                  "x": 210,
                  "y": 146,
                  "capInsetsHeight": 1,
                  "capInsetsWidth": 1,
                  "capInsetsX": 0,
                  "capInsetsY": 0,
                  "fileName": null,
                  "fileNameData": {
                    "path": "ui24.png",
                    "plistFile": "ui1.plist",
                    "resourceType": 1
                  },
                  "scale9Enable": false,
                  "scale9Height": 60,
                  "scale9Width": 60
                }
              },
              {
                "classname": "ImageView",
                "name": null,
                "children": [],
                "options": {
                  "__type": "ImageViewSurrogate:#EditorCommon.JsonModel.Component.GUI",
                  "classname": "ImageView",
                  "name": "Image_100",
                  "ZOrder": 0,
                  "actiontag": 66357535,
                  "anchorPointX": 0.5,
                  "anchorPointY": 0.5,
                  "classType": "CocoStudio.EngineAdapterWrap.CSImageView",
                  "colorB": 255,
                  "colorG": 255,
                  "colorR": 255,
                  "customProperty": "",
                  "flipX": false,
                  "flipY": false,
                  "height": 2,
                  "ignoreSize": true,
                  "layoutParameter": null,
                  "opacity": 255,
                  "positionPercentX": -0.219230771,
                  "positionPercentY": 0.4225,
                  "positionType": 0,
                  "rotation": 0,
                  "scaleX": 1,
                  "scaleY": 1,
                  "sizePercentX": 0.461538464,
                  "sizePercentY": 0.005,
                  "sizeType": 0,
                  "tag": 128,
                  "touchAble": false,
                  "useMergedTexture": false,
                  "visible": true,
                  "width": 240,
                  "x": -114,
                  "y": 169,
                  "capInsetsHeight": 1,
                  "capInsetsWidth": 1,
                  "capInsetsX": 0,
                  "capInsetsY": 0,
                  "fileName": null,
                  "fileNameData": {
                    "path": "ui33.png",
                    "plistFile": "ui1.plist",
                    "resourceType": 1
                  },
                  "scale9Enable": false,
                  "scale9Height": 2,
                  "scale9Width": 240
                }
              },
              {
                "classname": "ImageView",
                "name": null,
                "children": [],
                "options": {
                  "__type": "ImageViewSurrogate:#EditorCommon.JsonModel.Component.GUI",
                  "classname": "ImageView",
                  "name": "Image_100_0",
                  "ZOrder": 0,
                  "actiontag": 38708033,
                  "anchorPointX": 0.5,
                  "anchorPointY": 0.5,
                  "classType": "CocoStudio.EngineAdapterWrap.CSImageView",
                  "colorB": 255,
                  "colorG": 255,
                  "colorR": 255,
                  "customProperty": "",
                  "flipX": false,
                  "flipY": false,
                  "height": 2,
                  "ignoreSize": true,
                  "layoutParameter": null,
                  "opacity": 255,
                  "positionPercentX": 0.223076925,
                  "positionPercentY": 0.4225,
                  "positionType": 0,
                  "rotation": 0,
                  "scaleX": 1,
                  "scaleY": 1,
                  "sizePercentX": 0.461538464,
                  "sizePercentY": 0.005,
                  "sizeType": 0,
                  "tag": 131,
                  "touchAble": false,
                  "useMergedTexture": false,
                  "visible": true,
                  "width": 240,
                  "x": 116,
                  "y": 169,
                  "capInsetsHeight": 1,
                  "capInsetsWidth": 1,
                  "capInsetsX": 0,
                  "capInsetsY": 0,
                  "fileName": null,
                  "fileNameData": {
                    "path": "ui33.png",
                    "plistFile": "ui1.plist",
                    "resourceType": 1
                  },
                  "scale9Enable": false,
                  "scale9Height": 2,
                  "scale9Width": 240
                }
              },
              {
                "classname": "ImageView",
                "name": null,
                "children": [],
                "options": {
                  "__type": "ImageViewSurrogate:#EditorCommon.JsonModel.Component.GUI",
                  "classname": "ImageView",
                  "name": "Image_100_1",
                  "ZOrder": 0,
                  "actiontag": 15167470,
                  "anchorPointX": 0.5,
                  "anchorPointY": 0.5,
                  "classType": "CocoStudio.EngineAdapterWrap.CSImageView",
                  "colorB": 255,
                  "colorG": 255,
                  "colorR": 255,
                  "customProperty": "",
                  "flipX": false,
                  "flipY": false,
                  "height": 2,
                  "ignoreSize": true,
                  "layoutParameter": null,
                  "opacity": 255,
                  "positionPercentX": -0.217307687,
                  "positionPercentY": 0.305,
                  "positionType": 0,
                  "rotation": 0,
                  "scaleX": 1,
                  "scaleY": 1,
                  "sizePercentX": 0.461538464,
                  "sizePercentY": 0.005,
                  "sizeType": 0,
                  "tag": 133,
                  "touchAble": false,
                  "useMergedTexture": false,
                  "visible": true,
                  "width": 240,
                  "x": -113,
                  "y": 122,
                  "capInsetsHeight": 1,
                  "capInsetsWidth": 1,
                  "capInsetsX": 0,
                  "capInsetsY": 0,
                  "fileName": null,
                  "fileNameData": {
                    "path": "ui33.png",
                    "plistFile": "ui1.plist",
                    "resourceType": 1
                  },
                  "scale9Enable": false,
                  "scale9Height": 2,
                  "scale9Width": 240
                }
              },
              {
                "classname": "ImageView",
                "name": null,
                "children": [],
                "options": {
                  "__type": "ImageViewSurrogate:#EditorCommon.JsonModel.Component.GUI",
                  "classname": "ImageView",
                  "name": "Image_100_1_2",
                  "ZOrder": 0,
                  "actiontag": 21497137,
                  "anchorPointX": 0.5,
                  "anchorPointY": 0.5,
                  "classType": "CocoStudio.EngineAdapterWrap.CSImageView",
                  "colorB": 255,
                  "colorG": 255,
                  "colorR": 255,
                  "customProperty": "",
                  "flipX": false,
                  "flipY": false,
                  "height": 2,
                  "ignoreSize": true,
                  "layoutParameter": null,
                  "opacity": 255,
                  "positionPercentX": 0.223076925,
                  "positionPercentY": 0.3025,
                  "positionType": 0,
                  "rotation": 0,
                  "scaleX": 1,
                  "scaleY": 1,
                  "sizePercentX": 0.461538464,
                  "sizePercentY": 0.005,
                  "sizeType": 0,
                  "tag": 136,
                  "touchAble": false,
                  "useMergedTexture": false,
                  "visible": true,
                  "width": 240,
                  "x": 116,
                  "y": 121,
                  "capInsetsHeight": 1,
                  "capInsetsWidth": 1,
                  "capInsetsX": 0,
                  "capInsetsY": 0,
                  "fileName": null,
                  "fileNameData": {
                    "path": "ui33.png",
                    "plistFile": "ui1.plist",
                    "resourceType": 1
                  },
                  "scale9Enable": false,
                  "scale9Height": 2,
                  "scale9Width": 240
                }
              },
              {
                "classname": "ImageView",
                "name": null,
                "children": [
                  {
                    "classname": "Label",
                    "name": null,
                    "children": [],
                    "options": {
                      "__type": "LabelSurrogate:#EditorCommon.JsonModel.Component.GUI",
                      "classname": "Label",
                      "name": "Label_15",
                      "ZOrder": 0,
                      "actiontag": 31616714,
                      "anchorPointX": 0,
                      "anchorPointY": 0.5,
                      "classType": "CocoStudio.EngineAdapterWrap.CSLabel",
                      "colorB": 0,
                      "colorG": 0,
                      "colorR": 0,
                      "customProperty": "",
                      "flipX": false,
                      "flipY": false,
                      "height": 32,
                      "ignoreSize": true,
                      "layoutParameter": null,
                      "opacity": 255,
                      "positionPercentX": -0.459259868,
                      "positionPercentY": 0.328395158,
                      "positionType": 0,
                      "rotation": 0,
                      "scaleX": 1,
                      "scaleY": 1,
                      "sizePercentX": 0.211111113,
                      "sizePercentY": 0.12,
                      "sizeType": 0,
                      "tag": 238,
                      "touchAble": false,
                      "useMergedTexture": false,
                      "visible": true,
                      "width": 200,
                      "x": -206,
                      "y": 73,
                      "areaHeight": 0,
                      "areaWidth": 0,
                      "fontFile": null,
                      "fontName": "微软雅黑",
                      "fontSize": 25,
                      "hAlignment": 0,
                      "text": "请输入道具数量：",
                      "touchScaleEnable": false,
                      "vAlignment": 0
                    }
                  },
                  {
                    "classname": "ImageView",
                    "name": null,
                    "children": [
                      {
                        "classname": "Label",
                        "name": null,
                        "children": [],
                        "options": {
                          "__type": "LabelSurrogate:#EditorCommon.JsonModel.Component.GUI",
                          "classname": "Label",
                          "name": "numLb",
                          "ZOrder": 0,
                          "actiontag": 53823119,
                          "anchorPointX": 0.5,
                          "anchorPointY": 0.5,
                          "classType": "CocoStudio.EngineAdapterWrap.CSLabel",
                          "colorB": 255,
                          "colorG": 255,
                          "colorR": 255,
                          "customProperty": "",
                          "flipX": false,
                          "flipY": false,
                          "height": 27,
                          "ignoreSize": true,
                          "layoutParameter": null,
                          "opacity": 255,
                          "positionPercentX": 0,
                          "positionPercentY": 0,
                          "positionType": 0,
                          "rotation": 0,
                          "scaleX": 1,
                          "scaleY": 1,
                          "sizePercentX": 0.452380955,
                          "sizePercentY": 0.7714286,
                          "sizeType": 0,
                          "tag": 252,
                          "touchAble": false,
                          "useMergedTexture": false,
                          "visible": true,
                          "width": 12,
                          "x": 0,
                          "y": 0,
                          "areaHeight": 0,
                          "areaWidth": 0,
                          "fontFile": null,
                          "fontName": "微软雅黑",
                          "fontSize": 20,
                          "hAlignment": 0,
                          "text": "1",
                          "touchScaleEnable": false,
                          "vAlignment": 0
                        }
                      }
                    ],
                    "options": {
                      "__type": "ImageViewSurrogate:#EditorCommon.JsonModel.Component.GUI",
                      "classname": "ImageView",
                      "name": "Image_19",
                      "ZOrder": 0,
                      "actiontag": 17288998,
                      "anchorPointX": 0.5,
                      "anchorPointY": 0.5,
                      "classType": "CocoStudio.EngineAdapterWrap.CSImageView",
                      "colorB": 255,
                      "colorG": 255,
                      "colorR": 255,
                      "customProperty": "",
                      "flipX": false,
                      "flipY": false,
                      "height": 35,
                      "ignoreSize": false,
                      "layoutParameter": null,
                      "opacity": 255,
                      "positionPercentX": -8.768169E-08,
                      "positionPercentY": -0.009876792,
                      "positionType": 0,
                      "rotation": 0,
                      "scaleX": 1,
                      "scaleY": 1,
                      "sizePercentX": 0.466666669,
                      "sizePercentY": 0.155555561,
                      "sizeType": 0,
                      "tag": 242,
                      "touchAble": false,
                      "useMergedTexture": false,
                      "visible": true,
                      "width": 210,
                      "x": 0,
                      "y": -2,
                      "capInsetsHeight": 1,
                      "capInsetsWidth": 1,
                      "capInsetsX": 15,
                      "capInsetsY": 15,
                      "fileName": null,
                      "fileNameData": {
                        "path": "ui23.png",
                        "plistFile": "ui1.plist",
                        "resourceType": 1
                      },
                      "scale9Enable": true,
                      "scale9Height": 35,
                      "scale9Width": 210
                    }
                  },
                  {
                    "classname": "Label",
                    "name": null,
                    "children": [],
                    "options": {
                      "__type": "LabelSurrogate:#EditorCommon.JsonModel.Component.GUI",
                      "classname": "Label",
                      "name": "Label_15_0",
                      "ZOrder": 0,
                      "actiontag": 6027230,
                      "anchorPointX": 0,
                      "anchorPointY": 0.5,
                      "classType": "CocoStudio.EngineAdapterWrap.CSLabel",
                      "colorB": 0,
                      "colorG": 0,
                      "colorR": 0,
                      "customProperty": "",
                      "flipX": false,
                      "flipY": false,
                      "height": 32,
                      "ignoreSize": true,
                      "layoutParameter": null,
                      "opacity": 255,
                      "positionPercentX": -0.459259927,
                      "positionPercentY": -0.318519026,
                      "positionType": 0,
                      "rotation": 0,
                      "scaleX": 1,
                      "scaleY": 1,
                      "sizePercentX": 0.211111113,
                      "sizePercentY": 0.12,
                      "sizeType": 0,
                      "tag": 245,
                      "touchAble": false,
                      "useMergedTexture": false,
                      "visible": true,
                      "width": 175,
                      "x": -206,
                      "y": -71,
                      "areaHeight": 0,
                      "areaWidth": 0,
                      "fontFile": null,
                      "fontName": "微软雅黑",
                      "fontSize": 25,
                      "hAlignment": 0,
                      "text": "出售获得银币：",
                      "touchScaleEnable": false,
                      "vAlignment": 0
                    }
                  },
                  {
                    "classname": "Label",
                    "name": null,
                    "children": [],
                    "options": {
                      "__type": "LabelSurrogate:#EditorCommon.JsonModel.Component.GUI",
                      "classname": "Label",
                      "name": "moneyLb",
                      "ZOrder": 0,
                      "actiontag": 23687908,
                      "anchorPointX": 0,
                      "anchorPointY": 0.5,
                      "classType": "CocoStudio.EngineAdapterWrap.CSLabel",
                      "colorB": 0,
                      "colorG": 0,
                      "colorR": 0,
                      "customProperty": "",
                      "flipX": false,
                      "flipY": false,
                      "height": 32,
                      "ignoreSize": true,
                      "layoutParameter": null,
                      "opacity": 255,
                      "positionPercentX": -0.04197589,
                      "positionPercentY": -0.318519026,
                      "positionType": 0,
                      "rotation": 0,
                      "scaleX": 1,
                      "scaleY": 1,
                      "sizePercentX": 0.211111113,
                      "sizePercentY": 0.12,
                      "sizeType": 0,
                      "tag": 247,
                      "touchAble": false,
                      "useMergedTexture": false,
                      "visible": true,
                      "width": 90,
                      "x": -18,
                      "y": -71,
                      "areaHeight": 0,
                      "areaWidth": 0,
                      "fontFile": null,
                      "fontName": "微软雅黑",
                      "fontSize": 25,
                      "hAlignment": 0,
                      "text": "999999",
                      "touchScaleEnable": false,
                      "vAlignment": 0
                    }
                  },
                  {
                    "classname": "Button",
                    "name": null,
                    "children": [],
                    "options": {
                      "__type": "ButtonSurrogate:#EditorCommon.JsonModel.Component.GUI",
                      "classname": "Button",
                      "name": "minus",
                      "ZOrder": 0,
                      "actiontag": 41936894,
                      "anchorPointX": 0.5,
                      "anchorPointY": 0.5,
                      "classType": "CocoStudio.EngineAdapterWrap.CSButton",
                      "colorB": 255,
                      "colorG": 255,
                      "colorR": 255,
                      "customProperty": "",
                      "flipX": false,
                      "flipY": false,
                      "height": 44,
                      "ignoreSize": true,
                      "layoutParameter": null,
                      "opacity": 255,
                      "positionPercentX": -0.2617284,
                      "positionPercentY": -0.007407503,
                      "positionType": 0,
                      "rotation": 0,
                      "scaleX": 1,
                      "scaleY": 1,
                      "sizePercentX": 0.228888884,
                      "sizePercentY": 0.177777782,
                      "sizeType": 0,
                      "tag": 249,
                      "touchAble": true,
                      "useMergedTexture": false,
                      "visible": true,
                      "width": 44,
                      "x": -117,
                      "y": -1,
                      "capInsetsHeight": 1,
                      "capInsetsWidth": 1,
                      "capInsetsX": 0,
                      "capInsetsY": 0,
                      "disabled": null,
                      "disabledData": {
                        "path": null,
                        "plistFile": null,
                        "resourceType": 0
                      },
                      "fontName": "微软雅黑",
                      "fontSize": 14,
                      "fontType": 0,
                      "normal": null,
                      "normalData": {
                        "path": "tpan12.png",
                        "plistFile": "ui1.plist",
                        "resourceType": 1
                      },
                      "pressed": null,
                      "pressedData": {
                        "path": null,
                        "plistFile": null,
                        "resourceType": 0
                      },
                      "scale9Enable": false,
                      "scale9Height": 44,
                      "scale9Width": 44,
                      "text": "",
                      "textColorB": 255,
                      "textColorG": 255,
                      "textColorR": 255
                    }
                  },
                  {
                    "classname": "Button",
                    "name": null,
                    "children": [],
                    "options": {
                      "__type": "ButtonSurrogate:#EditorCommon.JsonModel.Component.GUI",
                      "classname": "Button",
                      "name": "plus",
                      "ZOrder": 2,
                      "actiontag": 46464034,
                      "anchorPointX": 0.5,
                      "anchorPointY": 0.5,
                      "classType": "CocoStudio.EngineAdapterWrap.CSButton",
                      "colorB": 255,
                      "colorG": 255,
                      "colorR": 255,
                      "customProperty": "",
                      "flipX": false,
                      "flipY": false,
                      "height": 44,
                      "ignoreSize": true,
                      "layoutParameter": null,
                      "opacity": 255,
                      "positionPercentX": 0.2617284,
                      "positionPercentY": -0.0049382695,
                      "positionType": 0,
                      "rotation": 0,
                      "scaleX": 1,
                      "scaleY": 1,
                      "sizePercentX": 0.228888884,
                      "sizePercentY": 0.177777782,
                      "sizeType": 0,
                      "tag": 250,
                      "touchAble": true,
                      "useMergedTexture": false,
                      "visible": true,
                      "width": 44,
                      "x": 117,
                      "y": -1,
                      "capInsetsHeight": 1,
                      "capInsetsWidth": 1,
                      "capInsetsX": 0,
                      "capInsetsY": 0,
                      "disabled": null,
                      "disabledData": {
                        "path": null,
                        "plistFile": null,
                        "resourceType": 0
                      },
                      "fontName": "微软雅黑",
                      "fontSize": 14,
                      "fontType": 0,
                      "normal": null,
                      "normalData": {
                        "path": "tpan11.png",
                        "plistFile": "ui1.plist",
                        "resourceType": 1
                      },
                      "pressed": null,
                      "pressedData": {
                        "path": null,
                        "plistFile": null,
                        "resourceType": 0
                      },
                      "scale9Enable": false,
                      "scale9Height": 44,
                      "scale9Width": 44,
                      "text": "",
                      "textColorB": 255,
                      "textColorG": 255,
                      "textColorR": 255
                    }
                  }
                ],
                "options": {
                  "__type": "ImageViewSurrogate:#EditorCommon.JsonModel.Component.GUI",
                  "classname": "ImageView",
                  "name": "Image_content",
                  "ZOrder": 0,
                  "actiontag": 50665935,
                  "anchorPointX": 0.5,
                  "anchorPointY": 0.5,
                  "classType": "CocoStudio.EngineAdapterWrap.CSImageView",
                  "colorB": 255,
                  "colorG": 255,
                  "colorR": 255,
                  "customProperty": "",
                  "flipX": false,
                  "flipY": false,
                  "height": 225,
                  "ignoreSize": false,
                  "layoutParameter": null,
                  "opacity": 255,
                  "positionPercentX": 0,
                  "positionPercentY": 0,
                  "positionType": 0,
                  "rotation": 0,
                  "scaleX": 1,
                  "scaleY": 1,
                  "sizePercentX": 0.865384638,
                  "sizePercentY": 0.5625,
                  "sizeType": 0,
                  "tag": 140,
                  "touchAble": false,
                  "useMergedTexture": false,
                  "visible": true,
                  "width": 450,
                  "x": 0,
                  "y": 0,
                  "capInsetsHeight": 2,
                  "capInsetsWidth": 2,
                  "capInsetsX": 3,
                  "capInsetsY": 3,
                  "fileName": null,
                  "fileNameData": {
                    "path": "ui18.png",
                    "plistFile": "ui1.plist",
                    "resourceType": 1
                  },
                  "scale9Enable": true,
                  "scale9Height": 225,
                  "scale9Width": 450
                }
              },
              {
                "classname": "Label",
                "name": null,
                "children": [],
                "options": {
                  "__type": "LabelSurrogate:#EditorCommon.JsonModel.Component.GUI",
                  "classname": "Label",
                  "name": "titletext",
                  "ZOrder": 0,
                  "actiontag": 58947126,
                  "anchorPointX": 0.5,
                  "anchorPointY": 0.5,
                  "classType": "CocoStudio.EngineAdapterWrap.CSLabel",
                  "colorB": 70,
                  "colorG": 195,
                  "colorR": 245,
                  "customProperty": "",
                  "flipX": false,
                  "flipY": false,
                  "height": 0,
                  "ignoreSize": true,
                  "layoutParameter": null,
                  "opacity": 255,
                  "positionPercentX": 0,
                  "positionPercentY": 0.3625,
                  "positionType": 0,
                  "rotation": 0,
                  "scaleX": 1,
                  "scaleY": 1,
                  "sizePercentX": 1.92307689E-05,
                  "sizePercentY": 2.5E-05,
                  "sizeType": 0,
                  "tag": 137,
                  "touchAble": false,
                  "useMergedTexture": false,
                  "visible": true,
                  "width": 0,
                  "x": 0,
                  "y": 145,
                  "areaHeight": 0,
                  "areaWidth": 0,
                  "fontFile": null,
                  "fontName": "微软雅黑",
                  "fontSize": 38,
                  "hAlignment": 1,
                  "text": "",
                  "touchScaleEnable": false,
                  "vAlignment": 0
                }
              },
              {
                "classname": "Label",
                "name": null,
                "children": [],
                "options": {
                  "__type": "LabelSurrogate:#EditorCommon.JsonModel.Component.GUI",
                  "classname": "Label",
                  "name": "contenttext",
                  "ZOrder": 0,
                  "actiontag": 17466883,
                  "anchorPointX": 0.5,
                  "anchorPointY": 0.5,
                  "classType": "CocoStudio.EngineAdapterWrap.CSLabel",
                  "colorB": 10,
                  "colorG": 10,
                  "colorR": 10,
                  "customProperty": "",
                  "flipX": false,
                  "flipY": false,
                  "height": 0,
                  "ignoreSize": true,
                  "layoutParameter": null,
                  "opacity": 255,
                  "positionPercentX": 0,
                  "positionPercentY": 0,
                  "positionType": 0,
                  "rotation": 0,
                  "scaleX": 1,
                  "scaleY": 1,
                  "sizePercentX": 1.92307689E-05,
                  "sizePercentY": 2.5E-05,
                  "sizeType": 0,
                  "tag": 235,
                  "touchAble": false,
                  "useMergedTexture": false,
                  "visible": true,
                  "width": 0,
                  "x": 0,
                  "y": 0,
                  "areaHeight": 0,
                  "areaWidth": 0,
                  "fontFile": null,
                  "fontName": "微软雅黑",
                  "fontSize": 32,
                  "hAlignment": 1,
                  "text": "",
                  "touchScaleEnable": false,
                  "vAlignment": 1
                }
              },
              {
                "classname": "Button",
                "name": null,
                "children": [],
                "options": {
                  "__type": "ButtonSurrogate:#EditorCommon.JsonModel.Component.GUI",
                  "classname": "Button",
                  "name": "leftbtn",
                  "ZOrder": 0,
                  "actiontag": 40508790,
                  "anchorPointX": 0.5,
                  "anchorPointY": 0.5,
                  "classType": "CocoStudio.EngineAdapterWrap.CSButton",
                  "colorB": 255,
                  "colorG": 255,
                  "colorR": 255,
                  "customProperty": "",
                  "flipX": false,
                  "flipY": false,
                  "height": 60,
                  "ignoreSize": false,
                  "layoutParameter": null,
                  "opacity": 255,
                  "positionPercentX": -0.228846252,
                  "positionPercentY": -0.370000124,
                  "positionType": 0,
                  "rotation": 0,
                  "scaleX": 1,
                  "scaleY": 1,
                  "sizePercentX": 0.25,
                  "sizePercentY": 0.15,
                  "sizeType": 0,
                  "tag": 167,
                  "touchAble": true,
                  "useMergedTexture": false,
                  "visible": true,
                  "width": 130,
                  "x": -119,
                  "y": -148,
                  "capInsetsHeight": 40,
                  "capInsetsWidth": 40,
                  "capInsetsX": 12,
                  "capInsetsY": 12,
                  "disabled": null,
                  "disabledData": {
                    "path": null,
                    "plistFile": null,
                    "resourceType": 0
                  },
                  "fontName": "微软雅黑",
                  "fontSize": 25,
                  "fontType": 0,
                  "normal": null,
                  "normalData": {
                    "path": "button01.png",
                    "plistFile": "ui1.plist",
                    "resourceType": 1
                  },
                  "pressed": null,
                  "pressedData": {
                    "path": "button02.png",
                    "plistFile": "ui1.plist",
                    "resourceType": 1
                  },
                  "scale9Enable": true,
                  "scale9Height": 60,
                  "scale9Width": 130,
                  "text": "取  消",
                  "textColorB": 255,
                  "textColorG": 255,
                  "textColorR": 255
                }
              },
              {
                "classname": "Button",
                "name": null,
                "children": [],
                "options": {
                  "__type": "ButtonSurrogate:#EditorCommon.JsonModel.Component.GUI",
                  "classname": "Button",
                  "name": "rightbtn",
                  "ZOrder": 0,
                  "actiontag": 38187048,
                  "anchorPointX": 0.5,
                  "anchorPointY": 0.5,
                  "classType": "CocoStudio.EngineAdapterWrap.CSButton",
                  "colorB": 255,
                  "colorG": 255,
                  "colorR": 255,
                  "customProperty": "",
                  "flipX": false,
                  "flipY": false,
                  "height": 60,
                  "ignoreSize": false,
                  "layoutParameter": null,
                  "opacity": 255,
                  "positionPercentX": 0.224038348,
                  "positionPercentY": -0.370000124,
                  "positionType": 0,
                  "rotation": 0,
                  "scaleX": 1,
                  "scaleY": 1,
                  "sizePercentX": 0.25,
                  "sizePercentY": 0.15,
                  "sizeType": 0,
                  "tag": 231,
                  "touchAble": true,
                  "useMergedTexture": false,
                  "visible": true,
                  "width": 130,
                  "x": 116,
                  "y": -148,
                  "capInsetsHeight": 40,
                  "capInsetsWidth": 40,
                  "capInsetsX": 12,
                  "capInsetsY": 12,
                  "disabled": null,
                  "disabledData": {
                    "path": null,
                    "plistFile": null,
                    "resourceType": 0
                  },
                  "fontName": "微软雅黑",
                  "fontSize": 25,
                  "fontType": 0,
                  "normal": null,
                  "normalData": {
                    "path": "button01.png",
                    "plistFile": "ui1.plist",
                    "resourceType": 1
                  },
                  "pressed": null,
                  "pressedData": {
                    "path": "button02.png",
                    "plistFile": "ui1.plist",
                    "resourceType": 1
                  },
                  "scale9Enable": true,
                  "scale9Height": 60,
                  "scale9Width": 130,
                  "text": "确  定",
                  "textColorB": 255,
                  "textColorG": 255,
                  "textColorR": 255
                }
              }
            ],
            "options": {
              "__type": "ImageViewSurrogate:#EditorCommon.JsonModel.Component.GUI",
              "classname": "ImageView",
              "name": "Image_bk",
              "ZOrder": 0,
              "actiontag": 65531462,
              "anchorPointX": 0.5,
              "anchorPointY": 0.5,
              "classType": "CocoStudio.EngineAdapterWrap.CSImageView",
              "colorB": 255,
              "colorG": 255,
              "colorR": 255,
              "customProperty": "",
              "flipX": false,
              "flipY": false,
              "height": 400,
              "ignoreSize": false,
              "layoutParameter": {
                "classname": null,
                "name": null,
                "align": 5,
                "gravity": 0,
                "layoutEageType": 0,
                "layoutNormalHorizontal": 0,
                "layoutNormalVertical": 0,
                "layoutParentHorizontal": 0,
                "layoutParentVertical": 0,
                "marginDown": 0,
                "marginLeft": 310,
                "marginRight": 0,
                "marginTop": 120,
                "relativeName": "Image_bk",
                "relativeToName": "root",
                "type": 2
              },
              "opacity": 255,
              "positionPercentX": 0.5,
              "positionPercentY": 0.5,
              "positionType": 0,
              "rotation": 0,
              "scaleX": 1,
              "scaleY": 1,
              "sizePercentX": 0.5416667,
              "sizePercentY": 0.625,
              "sizeType": 0,
              "tag": 29,
              "touchAble": false,
              "useMergedTexture": false,
              "visible": true,
              "width": 520,
              "x": 480,
              "y": 320,
              "capInsetsHeight": 20,
              "capInsetsWidth": 20,
              "capInsetsX": 22,
              "capInsetsY": 22,
              "fileName": null,
              "fileNameData": {
                "path": "tankuang02.png",
                "plistFile": "ui1.plist",
                "resourceType": 1
              },
              "scale9Enable": true,
              "scale9Height": 400,
              "scale9Width": 520
            }
          }
        ],
        "options": {
          "__type": "PanelSurrogate:#EditorCommon.JsonModel.Component.GUI",
          "classname": "Panel",
          "name": "root",
          "ZOrder": 0,
          "actiontag": -1,
          "anchorPointX": 0,
          "anchorPointY": 0,
          "classType": "CocoStudio.EngineAdapterWrap.CSPanel",
          "colorB": 255,
          "colorG": 255,
          "colorR": 255,
          "customProperty": "",
          "flipX": false,
          "flipY": false,
          "height": 640,
          "ignoreSize": false,
          "layoutParameter": null,
          "opacity": 255,
          "positionPercentX": -0.00115744269,
          "positionPercentY": -0.00520831952,
          "positionType": 0,
          "rotation": 0,
          "scaleX": 1,
          "scaleY": 1,
          "sizePercentX": 1,
          "sizePercentY": 1,
          "sizeType": 0,
          "tag": 28,
          "touchAble": true,
          "useMergedTexture": false,
          "visible": true,
          "width": 960,
          "x": -1,
          "y": -3,
          "adaptScreen": false,
          "backGroundImage": null,
          "backGroundImageData": null,
          "backGroundScale9Enable": false,
          "bgColorB": 255,
          "bgColorG": 200,
          "bgColorOpacity": 0,
          "bgColorR": 150,
          "bgEndColorB": 255,
          "bgEndColorG": 200,
          "bgEndColorR": 150,
          "bgStartColorB": 255,
          "bgStartColorG": 255,
          "bgStartColorR": 255,
          "capInsetsHeight": 1,
          "capInsetsWidth": 1,
          "capInsetsX": 0,
          "capInsetsY": 0,
          "clipAble": false,
          "colorType": 1,
          "layoutType": 3,
          "vectorX": 0,
          "vectorY": -0.5
        }
      }
    ],
    "options": {
      "__type": "PanelSurrogate:#EditorCommon.JsonModel.Component.GUI",
      "classname": "Panel",
      "name": "Panel_14",
      "ZOrder": 0,
      "actiontag": 33757095,
      "anchorPointX": 0,
      "anchorPointY": 0,
      "classType": "CocoStudio.EngineAdapterWrap.CSPanel",
      "colorB": 255,
      "colorG": 255,
      "colorR": 255,
      "customProperty": "",
      "flipX": false,
      "flipY": false,
      "height": 640,
      "ignoreSize": false,
      "layoutParameter": null,
      "opacity": 255,
      "positionPercentX": 0,
      "positionPercentY": 0,
      "positionType": 0,
      "rotation": 0,
      "scaleX": 1,
      "scaleY": 1,
      "sizePercentX": 1,
      "sizePercentY": 1,
      "sizeType": 0,
      "tag": 3,
      "touchAble": true,
      "useMergedTexture": false,
      "visible": true,
      "width": 960,
      "x": 0,
      "y": 0,
      "adaptScreen": false,
      "backGroundImage": null,
      "backGroundImageData": null,
      "backGroundScale9Enable": false,
      "bgColorB": 255,
      "bgColorG": 200,
      "bgColorOpacity": 0,
      "bgColorR": 150,
      "bgEndColorB": 255,
      "bgEndColorG": 200,
      "bgEndColorR": 150,
      "bgStartColorB": 255,
      "bgStartColorG": 255,
      "bgStartColorR": 255,
      "capInsetsHeight": 1,
      "capInsetsWidth": 1,
      "capInsetsX": 0,
      "capInsetsY": 0,
      "clipAble": false,
      "colorType": 1,
      "layoutType": 0,
      "vectorX": 0,
      "vectorY": -0.5
    }
  }
}